.travis.yml
AUTHORS
ChangeLog
Dockerfile
LICENSE
README.md
docker-compose.yml
environment.yml
example_scenes.py
manim.py
manim_docker_diagram.png
requirements.txt
setup.cfg
setup.py
stage_scenes.py
.github/ISSUE_TEMPLATE.md
.github/PULL_REQUEST_TEMPLATE.md
docs/Makefile
docs/make.bat
docs/source/about.rst
docs/source/animation.rst
docs/source/conf.py
docs/source/constants.rst
docs/source/coordinate.rst
docs/source/index.rst
docs/source/assets/AnimationFadeIn.mp4
docs/source/assets/AnimationFadeInFrom.mp4
docs/source/assets/AnimationFadeInFromDiagonal.mp4
docs/source/assets/AnimationFadeInFromLarge.mp4
docs/source/assets/AnimationFadeInFromPoint.mp4
docs/source/assets/AnimationFadeInFromSmall.mp4
docs/source/assets/AnimationFadeOut.mp4
docs/source/assets/AnimationFadeOutAndShift.mp4
docs/source/assets/AnimationGrowFromCenter.mp4
docs/source/assets/AnimationGrowFromEdge.mp4
docs/source/assets/SquareToCircle.mp4
docs/source/assets/coordinate/CoorAlias.mp4
docs/source/assets/coordinate/CoorArithmetic.mp4
docs/source/assets/coordinate/CoorPolygon.png
docs/source/assets/coordinate/DotMap.mp4
docs/source/getting_started/animating_mobjects.rst
docs/source/getting_started/index.rst
docs/source/getting_started/learning_by_example.rst
docs/source/getting_started/making_a_scene.rst
docs/source/getting_started/mathematical_objects.rst
docs/source/installation/index.rst
docs/source/installation/linux.rst
docs/source/installation/mac.rst
docs/source/installation/windows.rst
from_3b1b/active/bayes/footnote.py
from_3b1b/active/bayes/part1.py
from_3b1b/active/diffyq/all_part1_scenes.py
from_3b1b/active/diffyq/all_part2_scenes.py
from_3b1b/active/diffyq/all_part3_scenes.py
from_3b1b/active/diffyq/all_part4_scenes.py
from_3b1b/active/diffyq/all_part5_scenes.py
from_3b1b/active/diffyq/fourier_montage_scenes.py
from_3b1b/active/diffyq/solve_pendulum_ode_sample_code.py
from_3b1b/active/diffyq/part1/pendulum.py
from_3b1b/active/diffyq/part1/phase_space.py
manimlib.egg-info/PKG-INFO
manimlib.egg-info/SOURCES.txt
manimlib.egg-info/dependency_links.txt
manimlib.egg-info/entry_points.txt
manimlib.egg-info/not-zip-safe
manimlib.egg-info/pbr.json
manimlib.egg-info/requires.txt
manimlib.egg-info/top_level.txt
