Metadata-Version: 2.1
Name: manimlib
Version: 0.2.0
Summary: Animation engine for explanatory math videos
Home-page: https://github.com/3b1b/manim
Author: Grant Sanderson
Author-email: grant@3blue1brown.com
License: MIT
Project-URL: Bug Tracker, https://github.com/3b1b/manim/issues
Project-URL: Documentation, https://eulertour.com/learn/manim
Project-URL: Source Code, https://github.com/3b1b/manim
Platform: UNKNOWN
